[
    {
        "key": "dbln",
        "value": "%7B%22100078093900872%22%3A%225XP37y8d%22%2C%2261554902347411%22%3A%22Rl1CfXoJ%22%2C%2261556566393688%22%3A%22EcSFsTqt%22%2C%2261554390830919%22%3A%22fz2DiYPW%22%7D",
        "domain": "facebook.com",
        "path": "/login/device-based/",
        "hostOnly": false,
        "creation": "2024-05-10T13:02:45.233Z",
        "lastAccessed": "2024-05-10T13:02:45.233Z"
    },
    {
        "key": "datr",
        "value": "WrMWZioUGIqK2vRW1D435jlU",
        "domain": "facebook.com",
        "path": "/",
        "hostOnly": false,
        "creation": "2024-05-10T13:02:45.233Z",
        "lastAccessed": "2024-05-10T13:02:45.233Z"
    },
    {
        "key": "sb",
        "value": "WrMWZq5XrIO8KymjNTakoG-N",
        "domain": "facebook.com",
        "path": "/",
        "hostOnly": false,
        "creation": "2024-05-10T13:02:45.233Z",
        "lastAccessed": "2024-05-10T13:02:45.233Z"
    },
    {
        "key": "m_ls",
        "value": "%7B%2261554902347411%22%3A%7B%22c%22%3A%7B%7D%2C%22d%22%3A%2286861dd3-bb56-4263-8ecb-c2b6165bedfd%22%2C%22s%22%3A%221%22%2C%22u%22%3A%22zfch3h%22%7D%7D",
        "domain": "facebook.com",
        "path": "/",
        "hostOnly": false,
        "creation": "2024-05-10T13:02:45.233Z",
        "lastAccessed": "2024-05-10T13:02:45.233Z"
    },
    {
        "key": "ps_n",
        "value": "1",
        "domain": "facebook.com",
        "path": "/",
        "hostOnly": false,
        "creation": "2024-05-10T13:02:45.233Z",
        "lastAccessed": "2024-05-10T13:02:45.233Z"
    },
    {
        "key": "ps_l",
        "value": "1",
        "domain": "facebook.com",
        "path": "/",
        "hostOnly": false,
        "creation": "2024-05-10T13:02:45.233Z",
        "lastAccessed": "2024-05-10T13:02:45.233Z"
    },
    {
        "key": "oo",
        "value": "v1",
        "domain": "facebook.com",
        "path": "/",
        "hostOnly": false,
        "creation": "2024-05-10T13:02:45.233Z",
        "lastAccessed": "2024-05-10T13:02:45.233Z"
    },
    {
        "key": "vpd",
        "value": "v1%3B668x360x3",
        "domain": "facebook.com",
        "path": "/",
        "hostOnly": false,
        "creation": "2024-05-10T13:02:45.233Z",
        "lastAccessed": "2024-05-10T13:02:45.233Z"
    },
    {
        "key": "dpr",
        "value": "3",
        "domain": "facebook.com",
        "path": "/",
        "hostOnly": false,
        "creation": "2024-05-10T13:02:45.233Z",
        "lastAccessed": "2024-05-10T13:02:45.233Z"
    },
    {
        "key": "m_pixel_ratio",
        "value": "3",
        "domain": "facebook.com",
        "path": "/",
        "hostOnly": false,
        "creation": "2024-05-10T13:02:45.233Z",
        "lastAccessed": "2024-05-10T13:02:45.233Z"
    },
    {
        "key": "wd",
        "value": "360x668",
        "domain": "facebook.com",
        "path": "/",
        "hostOnly": false,
        "creation": "2024-05-10T13:02:45.233Z",
        "lastAccessed": "2024-05-10T13:02:45.233Z"
    },
    {
        "key": "fr",
        "value": "0Tjp9ovMo7fwETMIx.AWWB37apslyV8Tx5GTsA2O6P1RM.BmInQ8..AAA.0.0.BmPhrp.AWXloOViV_8",
        "domain": "facebook.com",
        "path": "/",
        "hostOnly": false,
        "creation": "2024-05-10T13:02:45.233Z",
        "lastAccessed": "2024-05-10T13:02:45.233Z"
    },
    {
        "key": "c_user",
        "value": "61556566393688",
        "domain": "facebook.com",
        "path": "/",
        "hostOnly": false,
        "creation": "2024-05-10T13:02:45.233Z",
        "lastAccessed": "2024-05-10T13:02:45.233Z"
    },
    {
        "key": "xs",
        "value": "37%3AZQD7koXBIIbDzA%3A2%3A1715346154%3A-1%3A4129",
        "domain": "facebook.com",
        "path": "/",
        "hostOnly": false,
        "creation": "2024-05-10T13:02:45.233Z",
        "lastAccessed": "2024-05-10T13:02:45.233Z"
    },
    {
        "key": "locale",
        "value": "en_US",
        "domain": "facebook.com",
        "path": "/",
        "hostOnly": false,
        "creation": "2024-05-10T13:02:45.233Z",
        "lastAccessed": "2024-05-10T13:02:45.233Z"
    },
    {
        "key": "fbl_st",
        "value": "101323075%3BT%3A28589102",
        "domain": "facebook.com",
        "path": "/",
        "hostOnly": false,
        "creation": "2024-05-10T13:02:45.233Z",
        "lastAccessed": "2024-05-10T13:02:45.233Z"
    },
    {
        "key": "wl_cbv",
        "value": "v2%3Bclient_version%3A2496%3Btimestamp%3A1715346155",
        "domain": "facebook.com",
        "path": "/",
        "hostOnly": false,
        "creation": "2024-05-10T13:02:45.233Z",
        "lastAccessed": "2024-05-10T13:02:45.233Z"
    }
]
